odoo/addons/l10n_jp_country_state/README.rst
odoo/addons/l10n_jp_country_state/__init__.py
odoo/addons/l10n_jp_country_state/__manifest__.py
odoo/addons/l10n_jp_country_state/i18n/l10n_jp_country_state.pot
odoo/addons/l10n_jp_country_state/i18n_extra/ja.po
odoo/addons/l10n_jp_country_state/readme/CONTRIBUTORS.md
odoo/addons/l10n_jp_country_state/readme/DESCRIPTION.md
odoo/addons/l10n_jp_country_state/readme/INSTALL.md
odoo/addons/l10n_jp_country_state/static/description/icon.png
odoo/addons/l10n_jp_country_state/static/description/index.html
odoo_addon_l10n_jp_country_state-18.0.1.0.0.2.dist-info/METADATA
odoo_addon_l10n_jp_country_state-18.0.1.0.0.2.dist-info/WHEEL
odoo_addon_l10n_jp_country_state-18.0.1.0.0.2.dist-info/top_level.txt
odoo_addon_l10n_jp_country_state-18.0.1.0.0.2.dist-info/RECORD
